LICENSE.txt
MANIFEST.in
README.rst
bblame
setup.py
bblame.egg-info/PKG-INFO
bblame.egg-info/SOURCES.txt
bblame.egg-info/dependency_links.txt
bblame.egg-info/not-zip-safe
bblame.egg-info/requires.txt
bblame.egg-info/top_level.txt
betterblame/__init__.py
betterblame/__main__.py
betterblame/actions.py
betterblame/bblame.py
betterblame/content.py
betterblame/git.py
betterblame/highlight.py
betterblame/modes.py
betterblame/options.py
betterblame/screen.py
betterblame/search.py
betterblame/sh.py
betterblame/util.py
betterblame/version.py