Metadata-Version: 2.1
Name: bblame
Version: 0.7.0
Summary: An ncurses app for browsing file git history
Home-page: https://bitbucket.org/niko333/betterblame
Author: Niko Oliveira
Author-email: oliveira.n3@gmail.com
License: MIT
Keywords: better git blame history curses ncurses
Platform: UNKNOWN
Classifier: Development Status :: 4 - Beta
Classifier: Intended Audience :: Developers
Classifier: Topic :: Software Development :: Build Tools
Classifier: Environment :: Console :: Curses
Classifier: License :: OSI Approved :: MIT License
Classifier: Programming Language :: Python :: 3
License-File: LICENSE.txt
